<?xml version="1.0" encoding="UTF-8" standalone="yes"?>
<p:sldLayout xmlns:a="http://schemas.openxmlformats.org/drawingml/2006/main" xmlns:r="http://schemas.openxmlformats.org/officeDocument/2006/relationships" xmlns:p="http://schemas.openxmlformats.org/presentationml/2006/main" showMasterSp="0" type="obj" preserve="1"><p:cSld name="Título e Conteúdo"><p:spTree><p:nvGrpSpPr><p:cNvPr id="1" name=""/><p:cNvGrpSpPr/><p:nvPr/></p:nvGrpSpPr><p:grpSpPr><a:xfrm><a:off x="0" y="0"/><a:ext cx="0" cy="0"/><a:chOff x="0" y="0"/><a:chExt cx="0" cy="0"/></a:xfrm></p:grpSpPr><p:sp><p:nvSpPr><p:cNvPr id="4" name="Rectangle 6"/><p:cNvSpPr/><p:nvPr/></p:nvSpPr><p:spPr bwMode="white"><a:xfrm><a:off x="0" y="1235075"/><a:ext cx="9144000" cy="319088"/></a:xfrm><a:prstGeom prst="rect"><a:avLst/></a:prstGeom><a:solidFill><a:srgbClr val="FFFFFF"/></a:solidFill><a:ln w="50800" cap="rnd" cmpd="dbl" algn="ctr"><a:noFill/><a:prstDash val="solid"/></a:ln><a:effectLst/></p:spPr><p:style><a:lnRef idx="3"><a:schemeClr val="lt1"/></a:lnRef><a:fillRef idx="1"><a:schemeClr val="accent1"/></a:fillRef><a:effectRef idx="1"><a:schemeClr val="accent1"/></a:effectRef><a:fontRef idx="minor"><a:schemeClr val="lt1"/></a:fontRef></p:style><p:txBody><a:bodyPr anchor="ctr"/><a:lstStyle/><a:p><a:pPr algn="ctr" eaLnBrk="1" fontAlgn="auto" hangingPunct="1"><a:spcBef><a:spcPts val="0"/></a:spcBef><a:spcAft><a:spcPts val="0"/></a:spcAft><a:defRPr/></a:pPr><a:endParaRPr lang="pt-BR" dirty="0"/></a:p></p:txBody></p:sp><p:sp><p:nvSpPr><p:cNvPr id="5" name="Rectangle 7"/><p:cNvSpPr/><p:nvPr/></p:nvSpPr><p:spPr><a:xfrm><a:off x="0" y="1279525"/><a:ext cx="533400" cy="228600"/></a:xfrm><a:prstGeom prst="rect"><a:avLst/></a:prstGeom><a:solidFill><a:schemeClr val="accent2"><a:alpha val="100000"/></a:schemeClr></a:solidFill><a:ln w="50800" cap="rnd" cmpd="dbl" algn="ctr"><a:noFill/><a:prstDash val="solid"/></a:ln><a:effectLst/></p:spPr><p:style><a:lnRef idx="3"><a:schemeClr val="lt1"/></a:lnRef><a:fillRef idx="1"><a:schemeClr val="accent1"/></a:fillRef><a:effectRef idx="1"><a:schemeClr val="accent1"/></a:effectRef><a:fontRef idx="minor"><a:schemeClr val="lt1"/></a:fontRef></p:style><p:txBody><a:bodyPr anchor="ctr"/><a:lstStyle/><a:p><a:pPr algn="ctr" eaLnBrk="1" fontAlgn="auto" hangingPunct="1"><a:spcBef><a:spcPts val="0"/></a:spcBef><a:spcAft><a:spcPts val="0"/></a:spcAft><a:defRPr/></a:pPr><a:endParaRPr lang="pt-BR" dirty="0"/></a:p></p:txBody></p:sp><p:sp><p:nvSpPr><p:cNvPr id="6" name="Rectangle 8"/><p:cNvSpPr/><p:nvPr/></p:nvSpPr><p:spPr><a:xfrm><a:off x="590550" y="1279525"/><a:ext cx="8553450" cy="228600"/></a:xfrm><a:prstGeom prst="rect"><a:avLst/></a:prstGeom><a:solidFill><a:schemeClr val="accent1"><a:alpha val="100000"/></a:schemeClr></a:solidFill><a:ln w="50800" cap="rnd" cmpd="dbl" algn="ctr"><a:noFill/><a:prstDash val="solid"/></a:ln><a:effectLst/></p:spPr><p:style><a:lnRef idx="3"><a:schemeClr val="lt1"/></a:lnRef><a:fillRef idx="1"><a:schemeClr val="accent1"/></a:fillRef><a:effectRef idx="1"><a:schemeClr val="accent1"/></a:effectRef><a:fontRef idx="minor"><a:schemeClr val="lt1"/></a:fontRef></p:style><p:txBody><a:bodyPr anchor="ctr"/><a:lstStyle/><a:p><a:pPr algn="ctr" eaLnBrk="1" fontAlgn="auto" hangingPunct="1"><a:spcBef><a:spcPts val="0"/></a:spcBef><a:spcAft><a:spcPts val="0"/></a:spcAft><a:defRPr/></a:pPr><a:endParaRPr lang="pt-BR" dirty="0"/></a:p></p:txBody></p:sp><p:sp><p:nvSpPr><p:cNvPr id="2" name="Shape 1"/><p:cNvSpPr><a:spLocks noGrp="1"/></p:cNvSpPr><p:nvPr><p:ph type="title"/></p:nvPr></p:nvSpPr><p:spPr><a:xfrm><a:off x="612648" y="228600"/><a:ext cx="8153400" cy="990600"/></a:xfrm></p:spPr><p:txBody><a:bodyPr/><a:lstStyle/><a:p><a:r><a:rPr lang="pt-BR"/><a:t>Clique para editar o título mestre</a:t></a:r></a:p></p:txBody></p:sp><p:sp><p:nvSpPr><p:cNvPr id="8" name="Shape 7"/><p:cNvSpPr><a:spLocks noGrp="1"/></p:cNvSpPr><p:nvPr><p:ph sz="quarter" idx="1"/></p:nvPr></p:nvSpPr><p:spPr><a:xfrm><a:off x="612648" y="1600200"/><a:ext cx="8153400" cy="4495800"/></a:xfrm></p:spPr><p:txBody><a:bodyPr/><a:lstStyle/><a:p><a:pPr lvl="0"/><a:r><a:rPr lang="pt-BR"/><a:t>Clique para editar o texto mestre</a:t></a:r></a:p><a:p><a:pPr lvl="1"/><a:r><a:rPr lang="pt-BR"/><a:t>Segundo nível</a:t></a:r></a:p><a:p><a:pPr lvl="2"/><a:r><a:rPr lang="pt-BR"/><a:t>Terceiro nível</a:t></a:r></a:p><a:p><a:pPr lvl="3"/><a:r><a:rPr lang="pt-BR"/><a:t>Quarto nível</a:t></a:r></a:p><a:p><a:pPr lvl="4"/><a:r><a:rPr lang="pt-BR"/><a:t>Quinto nível</a:t></a:r></a:p></p:txBody></p:sp><p:sp><p:nvSpPr><p:cNvPr id="7" name="Shape 3"/><p:cNvSpPr><a:spLocks noGrp="1"/></p:cNvSpPr><p:nvPr><p:ph type="dt" sz="half" idx="10"/></p:nvPr></p:nvSpPr><p:spPr/><p:txBody><a:bodyPr/><a:lstStyle><a:lvl1pPr><a:defRPr/></a:lvl1pPr></a:lstStyle><a:p><a:pPr><a:defRPr/></a:pPr><a:fld id="{348B7C29-5114-6E4F-ACB5-E86E72D2CC9F}" type="datetime8"><a:rPr lang="en-US" smtClean="0"/><a:t>09/06/17 10:14</a:t></a:fld><a:endParaRPr dirty="0"/></a:p></p:txBody></p:sp><p:sp><p:nvSpPr><p:cNvPr id="9" name="Shape 4"/><p:cNvSpPr><a:spLocks noGrp="1"/></p:cNvSpPr><p:nvPr><p:ph type="ftr" sz="quarter" idx="11"/></p:nvPr></p:nvSpPr><p:spPr/><p:txBody><a:bodyPr/><a:lstStyle><a:lvl1pPr><a:defRPr/></a:lvl1pPr></a:lstStyle><a:p><a:pPr><a:defRPr/></a:pPr><a:endParaRPr dirty="0"/></a:p></p:txBody></p:sp><p:sp><p:nvSpPr><p:cNvPr id="10" name="Shape 5"/><p:cNvSpPr><a:spLocks noGrp="1"/></p:cNvSpPr><p:nvPr><p:ph type="sldNum" sz="quarter" idx="12"/></p:nvPr></p:nvSpPr><p:spPr><a:xfrm><a:off x="0" y="1271588"/><a:ext cx="533400" cy="244475"/></a:xfrm><a:prstGeom prst="rect"><a:avLst/></a:prstGeom></p:spPr><p:txBody><a:bodyPr/><a:lstStyle><a:lvl1pPr><a:defRPr sz="1400"><a:solidFill><a:srgbClr val="FFFFFF"/></a:solidFill></a:defRPr></a:lvl1pPr></a:lstStyle><a:p><a:fld id="{552ECE8C-316A-4354-A4B8-86A79814135A}" type="slidenum"><a:rPr lang="pt-BR" altLang="pt-BR"/><a:pPr/><a:t>‹#›</a:t></a:fld><a:endParaRPr lang="pt-BR" altLang="pt-BR" dirty="0"/></a:p></p:txBody></p:sp></p:spTree></p:cSld><p:clrMapOvr><a:masterClrMapping/></p:clrMapOvr></p:sldLayout>